Workbook

Sheet Paint Unified
A1: Vendor | B1: Sales Number | C1: Description | D1: Unit Price | E1: New Price | F1: Quantity | G1: U/M | H1: Tax | I1: Price GT | J1: % margin | K1: Price customer | L1: Coverage Sf | M1: Price Sf | N1: Application | O1: Column15 | P1: Column1 | R1: Ceiling average | S1: Ceiling median | T1: Max | U1: Min
A2: Sherwin Williams | B2: 650362817 | C2: PM 400 0 FL EXTRA Zero Voc Ceiling | D2: 26.54 | E2: 28.2651 | F2: 1 | G2: G | H2: 0.13 | I2: 31.939563 | J2: 0.05 | K2: 33.536541 | L2: 300 | M2: 0.12 | N2: Ceiling | R2: =AVERAGEA(M2:M4) -> 0.20333333 | S2: =MEDIAN(M2:M4) -> 0.17 | T2: =MAX(M2:M4) -> 0.32 | U2: =MIN(M2:M4) -> 0.12
A3: Benjamin Moore | B3: K50809-001 | C3: Waterborne Ceiling Paint White | D3: 51.69 | E3: 55.04985 | F3: 1 | G3: G | H3: 0.13 | I3: 62.20633 | J3: 0.05 | K3: 65.316647 | L3: 400 | M3: 0.17 | N3: Ceiling
A4: Benjamin Moore | B4: K5321X-001 | C4: Aura Bath & Spa Matte Base 1 | D4: 87.99 | E4: 93.70935 | F4: 1 | G4: G | H4: 0.13 | I4: 105.89157 | J4: 0.05 | K4: 111.18614 | L4: 350 | M4: 0.32 | N4: Ceiling/Finish | R4: Finish average | S4: Finish median | T4: Larger | U4: Min
A5: Sherwin Williams | B5: 650946627 | C5: PM 200 0 FL EXTRA Pro Mar 200 Zero Voc Contractor grade | D5: 31.69 | E5: 33.74985 | F5: 1 | G5: G | H5: 0.13 | I5: 38.13733 | J5: 0.05 | K5: 40.044197 | L5: 300 | M5: 0.14 | N5: Finish | R5: =AVERAGE(M5:M24) -> 0.309 | S5: =MEDIAN(M5:M24) -> 0.26 | T5: =MAX(M5:M24) -> 1.01 | U5: =MIN(M5:M24) -> 0.12
A6: Sherwin Williams | B6: 650991565 | C6: PM200 HP 0 EG EW Pro Mar 200 HP | D6: 40.49 | E6: 43.12185 | F6: 1 | G6: G | H6: 0.13 | I6: 48.72769 | J6: 0.05 | K6: 51.164075 | L6: 300 | M6: 0.18 | N6: Finish
A7: Sherwin Williams | B7: 651189276 | C7: SPR INT SA AIR EW SuperPaint Air | D7: 52.68 | E7: 56.1042 | F7: 1 | G7: G | H7: 0.13 | I7: 63.397746 | J7: 0.05 | K7: 66.567633 | L7: 300 | M7: 0.23 | N7: Finish | R7: Primer average | S7: Primer median | T7: Larger | U7: Min
A8: Sherwin Williams | B8: 651203143 | C8: SCUFF TUFF MT EW Scuff X Crossover | D8: 54 | E8: 57.51 | F8: 1 | G8: G | H8: 0.13 | I8: 64.9863 | J8: 0.05 | K8: 68.235615 | L8: 300 | M8: 0.23 | N8: Finish | R8: =AVERAGEA(M25:M29) -> 0.168 | S8: =MEDIAN(M25:M29) -> 0.09 | T8: =MAX(M25:M29) -> 0.36 | U8: =MIN(M25:M29) -> 0.07
A9: Sherwin Williams | B9: 651016966 | C9: EMERALD IN FL EXTR Emerald interior | D9: 60.19 | E9: 64.10235 | F9: 1 | G9: G | H9: 0.13 | I9: 72.435655 | J9: 0.05 | K9: 76.057438 | L9: 300 | M9: 0.26 | N9: Finish
A10: Sherwin Williams | B10: 650932056 | C10: CLRTP WBSTN WHT CAD Colour Top Ext Stain | D10: 40.53 | E10: 43.16445 | F10: 1 | G10: G | H10: 0.13 | I10: 48.775828 | J10: 0.05 | K10: 51.21462 | L10: 100 | M10: 0.52 | N10: Finish | R10: Total average
A11: Sherwin Williams | B11: 650952435 | C11: SPR EXT FL EXTRA SuperPaint Ext | D11: 51.52 | E11: 54.8688 | F11: 1 | G11: G | H11: 0.13 | I11: 62.001744 | J11: 0.05 | K11: 65.101831 | L11: 300 | M11: 0.22 | N11: Finish | R11: Special | S11: Standard | T11: Commercial
A12: Sherwin Williams | B12: 651201725 | C12: LATITUDE EXT FL EW | D12: 59.89 | E12: 63.78285 | F12: 1 | G12: G | H12: 0.13 | I12: 72.07462 | J12: 0.05 | K12: 75.678352 | L12: 300 | M12: 0.26 | N12: Finish | R12: =AVERAGE(T2,S5,R8) -> 0.24933333 | S12: =AVERAGE(S2,S5,S8) -> 0.17333333 | T12: =AVERAGEA(U2,U5,U8) -> 0.10333333
A13: Sherwin Williams | B13: 651254559 | C13: DURATION FL EXTRA | D13: 63.5 | E13: 67.6275 | F13: 1 | G13: G | H13: 0.13 | I13: 76.419075 | J13: 0.05 | K13: 80.240029 | L13: 250 | M13: 0.33 | N13: Finish
A14: Sherwin Williams | B14: 651032815 | C14: LXN XP EW Loxon XP | D14: 67.58 | E14: 71.9727 | F14: 1 | G14: G | H14: 0.13 | I14: 81.329151 | J14: 0.05 | K14: 85.395609 | L14: 85 | M14: 1.01 | N14: Finish
A15: Sherwin Williams | B15: 640118600 | C15: IND EN HS PUREWHT Industrial Enamel | D15: 55.59 | E15: 59.20335 | F15: 1 | G15: G | H15: 0.13 | I15: 66.899785 | J15: 0.05 | K15: 70.244775 | L15: 230 | M15: 0.31 | N15: Finish
A16: Benjamin Moore | B16: F5371X-001 | C16: Ultraspec Interior Low Sheen Base 1 | D16: 31.4 | E16: 33.441 | F16: 1 | G16: G | H16: 0.13 | I16: 37.78833 | J16: 0.05 | K16: 39.677746 | L16: 350 | M16: 0.12 | N16: Finish
A17: Benjamin Moore | B17: K4861X-001 | C17: Scuff X Interior Pearl finish base 1 | D17: 57.74 | E17: 61.4931 | F17: 1 | G17: G | H17: 0.13 | I17: 69.487203 | J17: 0.05 | K17: 72.961563 | L17: 350 | M17: 0.21 | N17: Finish
A18: Benjamin Moore | B18: F5521X-001 | C18: Regal Select Int Ulti-matte Base 1 | D18: 62.39 | E18: 66.44535 | F18: 1 | G18: G | H18: 0.13 | I18: 75.083245 | J18: 0.05 | K18: 78.837408 | L18: 400 | M18: 0.2 | N18: Finish
A19: Benjamin Moore | B19: K7921X-001 | C19: Advance Wb Alkyd Pearl Base 1 | D19: 65.99 | E19: 70.27935 | F19: 1 | G19: G | H19: 0.13 | I19: 79.415665 | J19: 0.05 | K19: 83.386449 | L19: 400 | M19: 0.21 | N19: Finish
A20: Benjamin Moore | B20: K4011X-001 | C20: Regal Select Ext Low Lustre Base 1 | D20: 83.59 | E20: 89.02335 | F20: 1 | G20: G | H20: 0.13 | I20: 100.59639 | J20: 0.05 | K20: 105.6262 | L20: 250 | M20: 0.43 | N20: Finish
A21: Benjamin Moore | B21: K6401X-001 | C21: Arborcoat Ext. Wb Stain Solid Base | D21: 63.79 | E21: 67.93635 | F21: 1 | G21: G | H21: 0.13 | I21: 76.768075 | J21: 0.05 | K21: 80.606479 | L21: 300 | M21: 0.27 | N21: Finish
A22: Benjamin Moore | B22: F6341X-001 | C22: Aura Exterior Low Lustre Base 1 | D22: 91.29 | E22: 97.22385 | F22: 1 | G22: G | H22: 0.13 | I22: 109.86295 | J22: 0.05 | K22: 115.3561 | L22: 250 | M22: 0.47 | N22: Finish
A23: Benjamin Moore | B23: V3922X-001 | C23: Corotech Command Acrylic Urethane Satin | D23: 71.49 | E23: 76.13685 | F23: 1 | G23: G | H23: 0.13 | I23: 86.03464 | J23: 0.05 | K23: 90.336373 | L23: 350 | M23: 0.26 | N23: Finish
A24: Benjamin Moore | B24: 13.36-001 | C24: Coronado Rust Scat Oil Accent Base | D24: 74.79 | E24: 79.65135 | F24: 1 | G24: G | H24: 0.13 | I24: 90.006026 | J24: 0.05 | K24: 94.506327 | L24: 300 | M24: 0.32 | N24: Finish
A25: Sherwin Williams | B25: 651252579 | C25: PVA INT PRMR WHITE Drywall Primer | D25: 17 | E25: 18.105 | F25: 1 | G25: G | H25: 0.13 | I25: 20.45865 | J25: 0.05 | K25: 21.481582 | L25: 350 | M25: 0.07 | N25: Primer
A26: Sherwin Williams | B26: 650259195 | C26: PM 200 0 PRIMER Zero VOC Primer | D26: 22.67 | E26: 24.14355 | F26: 1 | G26: G | H26: 0.13 | I26: 27.282211 | J26: 0.05 | K26: 28.646322 | L26: 350 | M26: 0.09 | N26: Primer
A27: Benjamin Moore | B27: K08200-001 | C27: Step One Primer - White | D27: 23.09 | E27: 24.59085 | F27: 1 | G27: G | H27: 0.13 | I27: 27.78766 | J27: 0.05 | K27: 29.177044 | L27: 400 | M27: 0.08 | N27: Primer
A28: Benjamin Moore | B28: SXA11009-01 | C28: Stix Urethane Acrylic Primer White | D28: 56.09 | E28: 59.73585 | F28: 1 | G28: G | H28: 0.13 | I28: 67.50151 | J28: 0.05 | K28: 70.876586 | L28: 300 | M28: 0.24 | N28: Primer
A29: Zinsser | C29: Bin Shellac Primer | D29: 98 | E29: 104.37 | F29: 1 | G29: G | H29: 0.13 | I29: 117.9381 | J29: 0.05 | K29: 123.835 | L29: 350 | M29: 0.36 | N29: Primer

Sheet Doors and accesories
B2: Type door | C2: Total area sf | D2: Labor Sf | E2: Paint Sf | F2: Value per door (1 coat) | H2: Accessories | I2: Area Sf per ft | J2: Labor Sf | K2: Paint Sf | L2: Value per Ft
B3: Single standard wood door | C3: =7*3*2 -> 42 | D3: 0.61 | E3: 0.22 | F3: =(C3*D3)+(E3*C3) -> 34.86 | H3: Baseboard | I3: =0.67*1 -> 0.67 | J3: 1.5 | K3: 0.22 | L3: =(K3*I3)+(J3*I3) -> 1.1524
B4: One and a half wood door | C4: =7*(3*1.5)*2 -> 63 | D4: 0.61 | E4: 0.22 | F4: =(C4*D4)+(E4*C4) -> 52.29 | H4: Crownmolding | I4: =0.71*1 -> 0.71 | J4: 2.5 | K4: 0.22 | L4: =(K4*I4)+(J4*I4) -> 1.9312
B5: Bi-fold wood door | C5: =6*7*2 -> 84 | D5: 0.61 | E5: 0.22 | F5: =(C5*D5)+(E5*C5) -> 69.72
B6: Single tall wood door | C6: =9*3*2 -> 54 | D6: 0.61 | E6: 0.22 | F6: =(C6*D6)+(E6*C6) -> 44.82
B7: One and a Half tall wood door | C7: =9*(3*1.5)*2 -> 81 | D7: 0.61 | E7: 0.22 | F7: =(C7*D7)+(E7*C7) -> 67.23
B8: Bi-fold tall wood door | C8: =6*9*2 -> 108 | D8: 0.61 | E8: 0.22 | F8: =(C8*D8)+(E8*C8) -> 89.64
B9: Single Metal man door | C9: =7*3*2 -> 42 | D9: 1.3 | E9: 0.33 | F9: =(C9*D9)+(E9*C9) -> 68.46
B10: One and a half Metal man door | C10: =7*(3*1.5)*2 -> 63 | D10: 1.3 | E10: 0.33 | F10: =(C10*D10)+(E10*C10) -> 102.69
B11: Bi-fold metal man door | C11: =6*7*2 -> 84 | D11: 1.3 | E11: 0.33 | F11: =(C11*D11)+(E11*C11) -> 136.92

Sheet Pivot Finish wall
A2: FINISH WALL PAINT
A3: Row Labels | B3: Sum of W Finish paint gal unit | C3: Round up gal | D3: Total Price
A4: 0 | B4: 0 | C4: =ROUNDUP('Pivot Finish wall'!B4,0) -> 0 | D4: =IFERROR(C4*VLOOKUP('Pivot Finish wall'!A4,'Paint Unified'!$C$2:$K$29,9,FALSE),0) -> 0
B5: 0 | C5: =ROUNDUP('Pivot Finish wall'!B5,0) -> 0 | D5: =IFERROR(C5*VLOOKUP('Pivot Finish wall'!A5,'Paint Unified'!$C$2:$K$29,9,FALSE),0) -> 0
A6: PM 200 0 FL EXTRA Pro Mar 200 Zero Voc Contractor grade | B6: 6 | C6: =ROUNDUP('Pivot Finish wall'!B6,0) -> 6 | D6: =IFERROR(C6*VLOOKUP('Pivot Finish wall'!A6,'Paint Unified'!$C$2:$K$29,9,FALSE),0) -> 240.26518
C7: =ROUNDUP('Pivot Finish wall'!B7,0) -> 0 | D7: =IFERROR(C7*VLOOKUP('Pivot Finish wall'!A7,'Paint Unified'!$C$2:$K$29,9,FALSE),0) -> 0
C8: =ROUNDUP('Pivot Finish wall'!B8,0) -> 0 | D8: =IFERROR(C8*VLOOKUP('Pivot Finish wall'!A8,'Paint Unified'!$C$2:$K$29,9,FALSE),0) -> 0
C9: =ROUNDUP('Pivot Finish wall'!B9,0) -> 0 | D9: =IFERROR(C9*VLOOKUP('Pivot Finish wall'!A9,'Paint Unified'!$C$2:$K$29,9,FALSE),0) -> 0
C10: =ROUNDUP('Pivot Finish wall'!B10,0) -> 0 | D10: =IFERROR(C10*VLOOKUP('Pivot Finish wall'!A10,'Paint Unified'!$C$2:$K$29,9,FALSE),0) -> 0
C11: =ROUNDUP('Pivot Finish wall'!B11,0) -> 0 | D11: =IFERROR(C11*VLOOKUP('Pivot Finish wall'!A11,'Paint Unified'!$C$2:$K$29,9,FALSE),0) -> 0
C12: =ROUNDUP([1]Calculations!C60,0) -> 0 | D12: =IFERROR(C12*VLOOKUP([1]Calculations!B60,'Paint Unified'!$C$2:$K$29,9,FALSE),0) -> 0
C13: =ROUNDUP([1]Calculations!C61,0) -> 0 | D13: =IFERROR(C13*VLOOKUP([1]Calculations!B61,'Paint Unified'!$C$2:$K$29,9,FALSE),0) -> 0
C14: =ROUNDUP([1]Calculations!C62,0) -> 0 | D14: =IFERROR(C14*VLOOKUP([1]Calculations!B62,'Paint Unified'!$C$2:$K$29,9,FALSE),0) -> 0
C15: =ROUNDUP([1]Calculations!C63,0) -> 0 | D15: =IFERROR(C15*VLOOKUP([1]Calculations!B63,'Paint Unified'!$C$2:$K$29,9,FALSE),0) -> 0
C16: =ROUNDUP([1]Calculations!C64,0) -> 0 | D16: =IFERROR(C16*VLOOKUP([1]Calculations!B64,'Paint Unified'!$C$2:$K$29,9,FALSE),0) -> 0
C17: =ROUNDUP([1]Calculations!C65,0) -> 0 | D17: =IFERROR(C17*VLOOKUP([1]Calculations!B65,'Paint Unified'!$C$2:$K$29,9,FALSE),0) -> 0
C18: =ROUNDUP([1]Calculations!C66,0) -> 0 | D18: =IFERROR(C18*VLOOKUP([1]Calculations!B66,'Paint Unified'!$C$2:$K$29,9,FALSE),0) -> 0
C19: =ROUNDUP([1]Calculations!C67,0) -> 0 | D19: =IFERROR(C19*VLOOKUP([1]Calculations!B67,'Paint Unified'!$C$2:$K$29,9,FALSE),0) -> 0
C20: =ROUNDUP([1]Calculations!C68,0) -> 0 | D20: =IFERROR(C20*VLOOKUP([1]Calculations!B68,'Paint Unified'!$C$2:$K$29,9,FALSE),0) -> 0
C21: =ROUNDUP([1]Calculations!C69,0) -> 0 | D21: =IFERROR(C21*VLOOKUP([1]Calculations!B69,'Paint Unified'!$C$2:$K$29,9,FALSE),0) -> 0
C22: =ROUNDUP([1]Calculations!C70,0) -> 0 | D22: =IFERROR(C22*VLOOKUP([1]Calculations!B70,'Paint Unified'!$C$2:$K$29,9,FALSE),0) -> 0
C23: =ROUNDUP([1]Calculations!C71,0) -> 0 | D23: =IFERROR(C23*VLOOKUP([1]Calculations!B71,'Paint Unified'!$C$2:$K$29,9,FALSE),0) -> 0

Sheet Pivot Finish Ceiling
A2: FINISH CEILING PAINT
A3: Row Labels | B3: Sum of C Finish paint gal unit | C3: Round up gal | D3: Total Price
A4: 0 | B4: 0 | C4: =ROUNDUP('Pivot Finish Ceiling'!B4,0) -> 0 | D4: =IFERROR(C4*VLOOKUP('Pivot Finish Ceiling'!A4,'Paint Unified'!$C$2:$K$29,9,FALSE),0) -> 0
A5: PM 400 0 FL EXTRA Zero Voc Ceiling | B5: 0 | C5: =ROUNDUP('Pivot Finish Ceiling'!B5,0) -> 0 | D5: =IFERROR(C5*VLOOKUP('Pivot Finish Ceiling'!A5,'Paint Unified'!$C$2:$K$29,9,FALSE),0) -> 0
C6: =ROUNDUP([1]Calculations!I54,0) -> 0 | D6: =IFERROR(C6*VLOOKUP([1]Calculations!H54,'Paint Unified'!$C$2:$K$29,9,FALSE),0) -> 0
C7: =ROUNDUP([1]Calculations!I55,0) -> 0 | D7: =IFERROR(C7*VLOOKUP([1]Calculations!H55,'Paint Unified'!$C$2:$K$29,9,FALSE),0) -> 0
C8: =ROUNDUP([1]Calculations!I56,0) -> 0 | D8: =IFERROR(C8*VLOOKUP([1]Calculations!H56,'Paint Unified'!$C$2:$K$29,9,FALSE),0) -> 0
C9: =ROUNDUP([1]Calculations!I57,0) -> 0 | D9: =IFERROR(C9*VLOOKUP([1]Calculations!H57,'Paint Unified'!$C$2:$K$29,9,FALSE),0) -> 0
C10: =ROUNDUP([1]Calculations!I58,0) -> 0 | D10: =IFERROR(C10*VLOOKUP([1]Calculations!H58,'Paint Unified'!$C$2:$K$29,9,FALSE),0) -> 0
C11: =ROUNDUP([1]Calculations!I59,0) -> 0 | D11: =IFERROR(C11*VLOOKUP([1]Calculations!H59,'Paint Unified'!$C$2:$K$29,9,FALSE),0) -> 0
C12: =ROUNDUP([1]Calculations!I60,0) -> 0 | D12: =IFERROR(C12*VLOOKUP([1]Calculations!H60,'Paint Unified'!$C$2:$K$29,9,FALSE),0) -> 0
C13: =ROUNDUP([1]Calculations!I61,0) -> 0 | D13: =IFERROR(C13*VLOOKUP([1]Calculations!H61,'Paint Unified'!$C$2:$K$29,9,FALSE),0) -> 0
C14: =ROUNDUP([1]Calculations!I62,0) -> 0 | D14: =IFERROR(C14*VLOOKUP([1]Calculations!H62,'Paint Unified'!$C$2:$K$29,9,FALSE),0) -> 0
C15: =ROUNDUP([1]Calculations!I63,0) -> 0 | D15: =IFERROR(C15*VLOOKUP([1]Calculations!H63,'Paint Unified'!$C$2:$K$29,9,FALSE),0) -> 0
C16: =ROUNDUP([1]Calculations!I64,0) -> 0 | D16: =IFERROR(C16*VLOOKUP([1]Calculations!H64,'Paint Unified'!$C$2:$K$29,9,FALSE),0) -> 0
C17: =ROUNDUP([1]Calculations!I65,0) -> 0 | D17: =IFERROR(C17*VLOOKUP([1]Calculations!H65,'Paint Unified'!$C$2:$K$29,9,FALSE),0) -> 0
... C23: =ROUNDUP([1]Calculations!I71,0) -> 0 | D23: =IFERROR(C23*VLOOKUP([1]Calculations!H71,'Paint Unified'!$C$2:$K$29,9,FALSE),0) -> 0
